magiccommits/__init__.py
magiccommits/main.py
magiccommits/src/__init__.py
magiccommits/src/commands/__init__.py
magiccommits/src/commands/config.py
magiccommits/src/commands/mc.py
magiccommits/src/exception/__init__.py
magiccommits/src/exception/error.py
magiccommits/src/exception/error_handler.py
magiccommits/src/utils/__init__.py
magiccommits/src/utils/git.py
magiccommits/src/utils/open_ai_commit.py
magiccommits/src/utils/prompt.py
magiccommits/src/utils/style.py
magiccommits/src/utils/test.py
magiccommits/src/utils/config/__init__.py
magiccommits/src/utils/config/config_helper.py
magiccommits/src/utils/config/config_parser.py
magiccommits/src/utils/config/config_response.py
magiccommits/src/utils/custom/__init__.py
magiccommits/src/utils/custom/confirmation_input.py
magiccommits/src/utils/custom/input_validator.py
magiccommits/src/utils/custom/interactive_terminal.py
magiccommits/src/utils/custom/loading.py
magiccommits-1.0.dev0.dist-info/LICENSE
magiccommits-1.0.dev0.dist-info/METADATA
magiccommits-1.0.dev0.dist-info/WHEEL
magiccommits-1.0.dev0.dist-info/entry_points.txt
magiccommits-1.0.dev0.dist-info/top_level.txt
magiccommits-1.0.dev0.dist-info/RECORD
