Metadata-Version: 2.1
Name: magiccommits
Version: 1.0.dev0
Summary: Magiccommit: Effortless Git Commits with AI
Home-page: https://github.com/prakash-O4/magiccommits
Author: Prakash Basnet
License: MIT
Keywords: Git,Commits,Automation,Code,Version,Control,ai commit,Commit messages
Classifier: Programming Language :: Python :: 3.8
Classifier: Programming Language :: Python :: 3.9
Classifier: Programming Language :: Python :: 3.10
Classifier: Programming Language :: Python :: 3.11
Classifier: License :: OSI Approved :: MIT License
License-File: LICENSE
Requires-Dist: click
Requires-Dist: pyperclip
Requires-Dist: readchar
